ruly/__init__.py
ruly/common.py
ruly/conditions.py
ruly/evaluator.py
ruly/knowledge_base.py
ruly/parser.py
ruly-0.1.0.dist-info/LICENSE
ruly-0.1.0.dist-info/METADATA
ruly-0.1.0.dist-info/WHEEL
ruly-0.1.0.dist-info/top_level.txt
ruly-0.1.0.dist-info/RECORD
