Metadata-Version: 2.1
Name: ruly
Version: 0.1.0
Summary: Simple, extensible rule engine in Python
Author-email: Zlatan Sičanica <zlatan.sicanica@gmail.com>
License: Copyright (c) 2020 Zlatan Sičanica
Project-URL: GitHub, https://github.com/zlatsic/ruly
Project-URL: Docs, https://ruly.readthedocs.io/en/latest/
Classifier: Development Status :: 1 - Planning
Classifier: Intended Audience :: Developers
Classifier: License :: OSI Approved :: MIT License
Classifier: Natural Language :: English
Classifier: Operating System :: OS Independent
Classifier: Programming Language :: Python :: 3.6
Classifier: Topic :: Software Development :: Libraries
Classifier: Topic :: Utilities
License-File: LICENSE
